pdftext/extraction.py
pdftext/pdf/chars.py
pdftext/pdf/links.py
pdftext/pdf/pages.py
pdftext/pdf/utils.py
pdftext/postprocessing.py
pdftext/schema.py
pdftext/scripts/extract_text.py
pdftext/settings.py
pdftext/tables.py
pdftext-0.6.2.dist-info/LICENSE
pdftext-0.6.2.dist-info/METADATA
pdftext-0.6.2.dist-info/WHEEL
pdftext-0.6.2.dist-info/entry_points.txt
pdftext-0.6.2.dist-info/RECORD
