Metadata-Version: 2.3
Name: pdftext
Version: 0.6.2
Summary: Extract structured text from pdfs quickly
License: Apache-2.0
Keywords: pdf,text,extraction
Author: Vik Paruchuri
Author-email: vik.paruchuri@gmail.com
Requires-Python: >=3.10,<4.0
Classifier: License :: OSI Approved :: Apache Software License
Classifier: Programming Language :: Python :: 3
Classifier: Programming Language :: Python :: 3.10
Classifier: Programming Language :: Python :: 3.11
Classifier: Programming Language :: Python :: 3.12
Classifier: Programming Language :: Python :: 3.13
Requires-Dist: click (>=8.1.8,<9.0.0)
Requires-Dist: pydantic (>=2.7.1,<3.0.0)
Requires-Dist: pydantic-settings (>=2.2.1,<3.0.0)
Requires-Dist: pypdfium2 (==4.30.0)
Project-URL: Repository, https://github.com/VikParuchuri/pdftext
